ppcmd/__init__.py
ppcmd/common/__init__.py
ppcmd/common/date_format.py
ppcmd/common/exit_code.py
ppcmd/common/file_list.py
ppcmd/common/git.py
ppcmd/common/location_check.py
ppcmd/common/path.py
ppcmd/common/print.py
ppcmd/common/run.py
ppcmd/common/sys.py
ppcmd/ppc/__init__.py
ppcmd/ppc/params.py
ppcmd/ppc/ppc.py
ppcmd/ppc/ppc_processor.py
ppcmd/ppc/version.py
ppcmd-0.3.6.dist-info/LICENSE
ppcmd-0.3.6.dist-info/METADATA
ppcmd-0.3.6.dist-info/WHEEL
ppcmd-0.3.6.dist-info/entry_points.txt
ppcmd-0.3.6.dist-info/top_level.txt
ppcmd-0.3.6.dist-info/RECORD
